sa2_seed_key/__init__.py
sa2_seed_key/sa2_seed_key.py
sa2_seed_key-0.0.1.dist-info/METADATA
sa2_seed_key-0.0.1.dist-info/WHEEL
sa2_seed_key-0.0.1.dist-info/top_level.txt
sa2_seed_key-0.0.1.dist-info/RECORD
