Metadata-Version: 2.1
Name: sa2-seed-key
Version: 0.0.1
Summary: SA2 Seed/Key Authorization for Volkswagen AG Vehicles
Home-page: https://github.com/bri3d/sa2_seed_key
Author: Brian Ledbetter
Author-email: brian@brianledbetter.com
License: UNKNOWN
Platform: UNKNOWN
Classifier: Programming Language :: Python :: 3
Classifier: License :: OSI Approved :: MIT License
Classifier: Operating System :: OS Independent
Requires-Python: >=3.6
